chronotype/__init__.py
chronotype/base.py
chronotype/containers.py
chronotype/exceptions.py
chronotype/interpolation.py
chronotype/numeric.py
chronotype/py.typed
chronotype/query.py
chronotype/utils.py
chronotype-0.1.1.dist-info/licenses/LICENSE
chronotype-0.1.1.dist-info/METADATA
chronotype-0.1.1.dist-info/WHEEL
chronotype-0.1.1.dist-info/top_level.txt
chronotype-0.1.1.dist-info/RECORD
