Metadata-Version: 2.4
Name: chronotype
Version: 0.1.1
Summary: Temporal-native data types where every value carries its full history
Author-email: Arli Turka <arliturka@gmail.com>
Maintainer-email: Arli Turka <arliturka@gmail.com>
License: MIT
Project-URL: Homepage, https://github.com/ArliT1-F/chronotype
Project-URL: Documentation, https://github.com/ArliT1-F/chronotype#readme
Project-URL: Repository, https://github.com/ArliT1-F/chronotype.git
Project-URL: Issues, https://github.com/ArliT1-F/chronotype/issues
Keywords: temporal,time-series,history,versioning,data-types,time-travel
Classifier: Development Status :: 4 - Beta
Classifier: Intended Audience :: Developers
Classifier: License :: OSI Approved :: MIT License
Classifier: Operating System :: OS Independent
Classifier: Programming Language :: Python :: 3
Classifier: Programming Language :: Python :: 3.9
Classifier: Programming Language :: Python :: 3.10
Classifier: Programming Language :: Python :: 3.11
Classifier: Programming Language :: Python :: 3.12
Classifier: Topic :: Software Development :: Libraries :: Python Modules
Classifier: Typing :: Typed
Requires-Python: >=3.9
License-File: LICENSE
Provides-Extra: dev
Requires-Dist: pytest>=7.0; extra == "dev"
Requires-Dist: pytest-cov>=4.0; extra == "dev"
Requires-Dist: mypy>=1.0; extra == "dev"
Requires-Dist: ruff>=0.1.0; extra == "dev"
Dynamic: license-file
